OfficeJiqiao1000Li/README.md
OfficeJiqiao1000Li/__init__.py
OfficeJiqiao1000Li/__main__.py
OfficeJiqiao1000Li/file.epub
OfficeJiqiao1000Li/index.html
OfficeJiqiao1000Li/css/__init__.py
OfficeJiqiao1000Li/css/annotations.css
OfficeJiqiao1000Li/css/main.css
OfficeJiqiao1000Li/css/normalize.css
OfficeJiqiao1000Li/css/popup.css
OfficeJiqiao1000Li/font/__init__.py
OfficeJiqiao1000Li/font/fontello.eot
OfficeJiqiao1000Li/font/fontello.svg
OfficeJiqiao1000Li/font/fontello.ttf
OfficeJiqiao1000Li/font/fontello.woff
OfficeJiqiao1000Li/img/__init__.py
OfficeJiqiao1000Li/img/annotator-glyph-sprite.png
OfficeJiqiao1000Li/img/annotator-icon-sprite.png
OfficeJiqiao1000Li/img/apple-touch-icon.png
OfficeJiqiao1000Li/img/cancelfullscreen.png
OfficeJiqiao1000Li/img/close.png
OfficeJiqiao1000Li/img/fullscreen.png
OfficeJiqiao1000Li/img/loader.gif
OfficeJiqiao1000Li/img/menu-icon.png
OfficeJiqiao1000Li/img/save.png
OfficeJiqiao1000Li/img/saved.png
OfficeJiqiao1000Li/img/settings-s.png
OfficeJiqiao1000Li/img/settings.png
OfficeJiqiao1000Li/img/star.png
OfficeJiqiao1000Li/js/__init__.py
OfficeJiqiao1000Li/js/epub.js
OfficeJiqiao1000Li/js/epub.min.js
OfficeJiqiao1000Li/js/epub.min.map
OfficeJiqiao1000Li/js/hooks.min.js
OfficeJiqiao1000Li/js/hooks.min.map
OfficeJiqiao1000Li/js/reader.js
OfficeJiqiao1000Li/js/reader.js.map
OfficeJiqiao1000Li/js/reader.min.js
OfficeJiqiao1000Li/js/reader.min.map
OfficeJiqiao1000Li/js/hooks/__init__.py
OfficeJiqiao1000Li/js/hooks/extensions/__init__.py
OfficeJiqiao1000Li/js/hooks/extensions/highlight.js
OfficeJiqiao1000Li/js/libs/__init__.py
OfficeJiqiao1000Li/js/libs/jquery.min.js
OfficeJiqiao1000Li/js/libs/localforage.min.js
OfficeJiqiao1000Li/js/libs/screenfull.js
OfficeJiqiao1000Li/js/libs/screenfull.min.js
OfficeJiqiao1000Li/js/libs/zip.min.js
OfficeJiqiao1000Li/js/plugins/__init__.py
OfficeJiqiao1000Li/js/plugins/hypothesis.js
OfficeJiqiao1000Li/js/plugins/search.js
office_jiqiao_1000_li-2024.3.2.0.dist-info/METADATA
office_jiqiao_1000_li-2024.3.2.0.dist-info/WHEEL
office_jiqiao_1000_li-2024.3.2.0.dist-info/entry_points.txt
office_jiqiao_1000_li-2024.3.2.0.dist-info/top_level.txt
office_jiqiao_1000_li-2024.3.2.0.dist-info/RECORD
